Gaussian_and_Binomial247/Binomialdistribution.py
Gaussian_and_Binomial247/Gaussiandistribution.py
Gaussian_and_Binomial247/Generaldistribution.py
Gaussian_and_Binomial247/__init__.py
Gaussian_and_Binomial247-0.1.dist-info/DESCRIPTION.rst
Gaussian_and_Binomial247-0.1.dist-info/METADATA
Gaussian_and_Binomial247-0.1.dist-info/RECORD
Gaussian_and_Binomial247-0.1.dist-info/WHEEL
Gaussian_and_Binomial247-0.1.dist-info/metadata.json
Gaussian_and_Binomial247-0.1.dist-info/top_level.txt
